loka/__init__.py
loka/__main__.py
loka/ai_lib.py
loka/cli.py
loka/code_generator.py
loka/interpreter.py
loka/lexer.py
loka/matrice.py
loka/matrix.py
loka/optimizer.py
loka/parser.py
loka_lang-0.3.0.dist-info/LICENSE
loka_lang-0.3.0.dist-info/METADATA
loka_lang-0.3.0.dist-info/WHEEL
loka_lang-0.3.0.dist-info/entry_points.txt
loka_lang-0.3.0.dist-info/top_level.txt
loka_lang-0.3.0.dist-info/RECORD
