Metadata-Version: 2.1
Name: loka-lang
Version: 0.3.0
Summary: Un langage de programmation moderne pour l'IA, créé par ALLE OSSEY ANGE CEDRIC
Home-page: https://github.com/cedric202012/loka
Author: LOKA Developer
Author-email: ALLE OSSEY ANGE CEDRIC <cedric.alle@example.com>
License: MIT License
Project-URL: Homepage, https://github.com/cedric202012/loka
Project-URL: Repository, https://github.com/cedric202012/loka.git
Keywords: programming-language,AI,machine-learning
Classifier: License :: OSI Approved :: MIT License
Classifier: Programming Language :: Python
Classifier: Programming Language :: Python :: 3
Requires-Python: >=3.8
License-File: LICENSE
Requires-Dist: llvmlite>=0.40.0
Requires-Dist: numpy>=1.21.0
Requires-Dist: scikit-learn>=1.0.0
Requires-Dist: numpy>=1.24.0
